<annotation><folder>mouse-teclado</folder><filename>de362873-dd9a-4ca2-8871-296e040edfff.jpg</filename><size><width>225</width><height>225</height><depth>3</depth></size><object><name>keyboard</name><pose>Unspecified</pose><truncated>0</truncated><difficult>0</difficult><bndbox><xmin>0</xmin><ymin>30</ymin><xmax>206</xmax><ymax>189</ymax></bndbox></object><object><name>mouse</name><pose>Unspecified</pose><truncated>0</truncated><difficult>0</difficult><bndbox><xmin>159</xmin><ymin>106</ymin><xmax>225</xmax><ymax>166</ymax></bndbox></object></annotation>